batch/__init__.py
batch/operations.py
batch_ops-0.1.dist-info/LICENSE
batch_ops-0.1.dist-info/METADATA
batch_ops-0.1.dist-info/WHEEL
batch_ops-0.1.dist-info/top_level.txt
batch_ops-0.1.dist-info/RECORD
